md_pro/__init__.py
md_pro/__main__.py
md_pro/src/__init__.py
md_pro/src/uc_mdp/__init__.py
md_pro/src/uc_mdp/mdp.py
md_pro/src/uc_mdp/problem.py
md_pro/src/uc_mdp/uc_mdp_main.py
md_pro/util/__init__.py
md_pro/util/data_input_loader.py
md_pro-0.0.13.dist-info/LICENSE
md_pro-0.0.13.dist-info/METADATA
md_pro-0.0.13.dist-info/WHEEL
md_pro-0.0.13.dist-info/top_level.txt
md_pro-0.0.13.dist-info/RECORD
